README.md
setup.py
src/ali_kms_sdk.egg-info/PKG-INFO
src/ali_kms_sdk.egg-info/SOURCES.txt
src/ali_kms_sdk.egg-info/dependency_links.txt
src/ali_kms_sdk.egg-info/requires.txt
src/ali_kms_sdk.egg-info/top_level.txt
src/aliyun_encryption_sdk/__init__.py
src/aliyun_encryption_sdk/client.py
src/aliyun_encryption_sdk/constants.py
src/aliyun_encryption_sdk/model.py
src/aliyun_encryption_sdk/cache/__init__.py
src/aliyun_encryption_sdk/cache/base.py
src/aliyun_encryption_sdk/cache/local.py
src/aliyun_encryption_sdk/ckm/__init__.py
src/aliyun_encryption_sdk/ckm/base.py
src/aliyun_encryption_sdk/ckm/cache.py
src/aliyun_encryption_sdk/ckm/default.py
src/aliyun_encryption_sdk/handle/__init__.py
src/aliyun_encryption_sdk/handle/encryption.py
src/aliyun_encryption_sdk/handle/format.py
src/aliyun_encryption_sdk/kms/__init__.py
src/aliyun_encryption_sdk/kms/kms.py
src/aliyun_encryption_sdk/provider/__init__.py
src/aliyun_encryption_sdk/provider/base.py
src/aliyun_encryption_sdk/provider/default.py
src/aliyun_encryption_sdk/provider/secret_manager.py
src/aliyun_encryption_sdk/provider/signature/__init__.py
src/aliyun_encryption_sdk/provider/signature/base.py
src/aliyun_encryption_sdk/provider/signature/verifier.py
test/test_crypto.py